clevrml.py
clevrml-0.9.1.dist-info/LICENSE.txt
clevrml-0.9.1.dist-info/METADATA
clevrml-0.9.1.dist-info/WHEEL
clevrml-0.9.1.dist-info/top_level.txt
clevrml-0.9.1.dist-info/RECORD
