Metadata-Version: 2.1
Name: clevrml
Version: 0.9.1
Summary: The Official Package for clevrML.
Home-page: UNKNOWN
License: Apache 2.0
Platform: UNKNOWN
Requires-Dist: Pillow (>=8.2.0)
